pipkin/__init__.py
pipkin/__main__.py
pipkin/adapters.py
pipkin/bare_metal.py
pipkin/common.py
pipkin/connection.py
pipkin/parser.py
pipkin/proxy.py
pipkin/serial_connection.py
pipkin/session.py
pipkin/util.py
pipkin/webrepl_connection.py
pipkin-2.1b1.dist-info/LICENSE
pipkin-2.1b1.dist-info/METADATA
pipkin-2.1b1.dist-info/WHEEL
pipkin-2.1b1.dist-info/entry_points.txt
pipkin-2.1b1.dist-info/top_level.txt
pipkin-2.1b1.dist-info/RECORD
